README.md
setup.py
coderdojo_minetest.egg-info/PKG-INFO
coderdojo_minetest.egg-info/SOURCES.txt
coderdojo_minetest.egg-info/dependency_links.txt
coderdojo_minetest.egg-info/top_level.txt
mcpi/__init__.py
mcpi/block.py
mcpi/connection.py
mcpi/entity.py
mcpi/event.py
mcpi/minecraft.py
mcpi/nbt.py
mcpi/settings.py
mcpi/util.py
mcpi/vec3.py