Metadata-Version: 1.0
Name: coderdojo-minetest
Version: 0.0.1
Summary: CoderDojo workshop module for minetest
Home-page: https://github.com/amigrave/coderdojo-minetest
Author: Fabien Meghazi
Author-email: agr@amigrave.com
License: MIT
Keywords: CoderDojo minetest
Platform: UNKNOWN
